daas_mcp_server/__init__.py
daas_mcp_server/__main__.py
daas_mcp_server/constants.py
daas_mcp_server/resources.py
daas_mcp_server/server.py
daas_mcp_server/tools.py
daas_mcp_server-0.0.3.dist-info/METADATA
daas_mcp_server-0.0.3.dist-info/WHEEL
daas_mcp_server-0.0.3.dist-info/entry_points.txt
daas_mcp_server-0.0.3.dist-info/top_level.txt
daas_mcp_server-0.0.3.dist-info/RECORD
