Metadata-Version: 2.4
Name: daas_mcp_server
Version: 0.0.3
Summary: DaaS MCP Server
Requires-Python: >=3.13
Requires-Dist: httpx>=0.28.1
Requires-Dist: langchain>=0.3.20
Requires-Dist: mcp[cli]>=1.3.0
Requires-Dist: python-dotenv>=1.0.1
Requires-Dist: rsa>=4.9
Provides-Extra: dev
Requires-Dist: mypy>=1.11.1; extra == "dev"
Requires-Dist: ruff>=0.6.1; extra == "dev"
Provides-Extra: rich
Requires-Dist: rich>=13.9.4; extra == "rich"
